screem/__init__.py
screem/screem.py
screem-2.0.0.dist-info/LICENSE
screem-2.0.0.dist-info/METADATA
screem-2.0.0.dist-info/WHEEL
screem-2.0.0.dist-info/top_level.txt
screem-2.0.0.dist-info/RECORD
