Metadata-Version: 2.1
Name: screem
Version: 2.0.0
Summary: Python3 package for creating graphical user interfaces inside a terminal 
Home-page: https://github.com/c0mplh4cks/screem
Author: c0mplh4cks
License: MIT
Platform: UNKNOWN
Requires-Python: >=3
